spotify_to_youtube/__init__.py
spotify_to_youtube/main.py
spotify_to_youtube/selenium_add_to_playlist.py
spotify_to_youtube/spotify.py
spotify_to_youtube/tests/test.py
spotify_to_youtube-0.1.3.dist-info/METADATA
spotify_to_youtube-0.1.3.dist-info/WHEEL
spotify_to_youtube-0.1.3.dist-info/entry_points.txt
spotify_to_youtube-0.1.3.dist-info/top_level.txt
spotify_to_youtube-0.1.3.dist-info/RECORD
