Metadata-Version: 2.2
Name: spotify-to-youtube
Version: 0.1.3
Summary: clones spotify playlist to youtube playlist
Author: Jonathan Z
Requires-Python: >=3.8
Requires-Dist: spotipy>=2.25.1
Requires-Dist: selenium>=4.29.0
Requires-Dist: PyYAML>=6.0.2
